datasette_quickchart/__init__.py
datasette_quickchart/static/main.css
datasette_quickchart/static/main.js
datasette_quickchart-0.1.1.dist-info/LICENSE
datasette_quickchart-0.1.1.dist-info/METADATA
datasette_quickchart-0.1.1.dist-info/WHEEL
datasette_quickchart-0.1.1.dist-info/entry_points.txt
datasette_quickchart-0.1.1.dist-info/top_level.txt
datasette_quickchart-0.1.1.dist-info/RECORD
