Metadata-Version: 2.1
Name: datasette-quickchart
Version: 0.1.1
Summary: Datasette plugin for making quick charts from tables and SQL queries using Apex Charts
Author: Witold Czarnecki
License: Apache-2.0
Project-URL: Homepage, https://github.com/commongeek/datasette-quickchart
Project-URL: Changelog, https://github.com/commongeek/datasette-quickchart/releases
Project-URL: Issues, https://github.com/commongeek/datasette-quickchart/issues
Project-URL: CI, https://github.com/commongeek/datasette-quickchart/actions
Classifier: Framework :: Datasette
Classifier: License :: OSI Approved :: Apache Software License
Requires-Python: >=3.9
License-File: LICENSE
Requires-Dist: datasette
Provides-Extra: test
Requires-Dist: pytest; extra == "test"
Requires-Dist: pytest-asyncio; extra == "test"
